X24XiaoshiWanzhuanMyetherwalletQianbaoKaifa/README.md
X24XiaoshiWanzhuanMyetherwalletQianbaoKaifa/__init__.py
X24XiaoshiWanzhuanMyetherwalletQianbaoKaifa/__main__.py
X24XiaoshiWanzhuanMyetherwalletQianbaoKaifa/file.epub
X24XiaoshiWanzhuanMyetherwalletQianbaoKaifa/index.html
X24XiaoshiWanzhuanMyetherwalletQianbaoKaifa/css/__init__.py
X24XiaoshiWanzhuanMyetherwalletQianbaoKaifa/css/annotations.css
X24XiaoshiWanzhuanMyetherwalletQianbaoKaifa/css/main.css
X24XiaoshiWanzhuanMyetherwalletQianbaoKaifa/css/normalize.css
X24XiaoshiWanzhuanMyetherwalletQianbaoKaifa/css/popup.css
X24XiaoshiWanzhuanMyetherwalletQianbaoKaifa/font/__init__.py
X24XiaoshiWanzhuanMyetherwalletQianbaoKaifa/font/fontello.eot
X24XiaoshiWanzhuanMyetherwalletQianbaoKaifa/font/fontello.svg
X24XiaoshiWanzhuanMyetherwalletQianbaoKaifa/font/fontello.ttf
X24XiaoshiWanzhuanMyetherwalletQianbaoKaifa/font/fontello.woff
X24XiaoshiWanzhuanMyetherwalletQianbaoKaifa/img/__init__.py
X24XiaoshiWanzhuanMyetherwalletQianbaoKaifa/img/annotator-glyph-sprite.png
X24XiaoshiWanzhuanMyetherwalletQianbaoKaifa/img/annotator-icon-sprite.png
X24XiaoshiWanzhuanMyetherwalletQianbaoKaifa/img/apple-touch-icon.png
X24XiaoshiWanzhuanMyetherwalletQianbaoKaifa/img/cancelfullscreen.png
X24XiaoshiWanzhuanMyetherwalletQianbaoKaifa/img/close.png
X24XiaoshiWanzhuanMyetherwalletQianbaoKaifa/img/fullscreen.png
X24XiaoshiWanzhuanMyetherwalletQianbaoKaifa/img/loader.gif
X24XiaoshiWanzhuanMyetherwalletQianbaoKaifa/img/menu-icon.png
X24XiaoshiWanzhuanMyetherwalletQianbaoKaifa/img/save.png
X24XiaoshiWanzhuanMyetherwalletQianbaoKaifa/img/saved.png
X24XiaoshiWanzhuanMyetherwalletQianbaoKaifa/img/settings-s.png
X24XiaoshiWanzhuanMyetherwalletQianbaoKaifa/img/settings.png
X24XiaoshiWanzhuanMyetherwalletQianbaoKaifa/img/star.png
X24XiaoshiWanzhuanMyetherwalletQianbaoKaifa/js/__init__.py
X24XiaoshiWanzhuanMyetherwalletQianbaoKaifa/js/epub.js
X24XiaoshiWanzhuanMyetherwalletQianbaoKaifa/js/epub.min.js
x24_xiaoshi_wanzhuan_myetherwallet_qianbao_kaifa-2024.3.5.0.dist-info/METADATA
x24_xiaoshi_wanzhuan_myetherwallet_qianbao_kaifa-2024.3.5.0.dist-info/WHEEL
x24_xiaoshi_wanzhuan_myetherwallet_qianbao_kaifa-2024.3.5.0.dist-info/entry_points.txt
x24_xiaoshi_wanzhuan_myetherwallet_qianbao_kaifa-2024.3.5.0.dist-info/top_level.txt
x24_xiaoshi_wanzhuan_myetherwallet_qianbao_kaifa-2024.3.5.0.dist-info/RECORD
